django_data_purger/__init__.py
django_data_purger/apps.py
django_data_purger/checks.py
django_data_purger/conf.py
django_data_purger/context.py
django_data_purger/data_purger.py
django_data_purger/enums.py
django_data_purger/exceptions.py
django_data_purger/management/__init__.py
django_data_purger/management/commands/__init__.py
django_data_purger/management/commands/calculate_model_dependencies.py
django_data_purger/management/commands/print_data_purging_enabled_tables.py
django_data_purger/management/commands/run_data_purgers.py
django_data_purger/py.typed
django_data_purger/services/__init__.py
django_data_purger/services/data_purger.py
django_data_purger/services/tables.py
django_data_purger/utils.py
django_data_purger-0.2.9.dist-info/METADATA
django_data_purger-0.2.9.dist-info/WHEEL
django_data_purger-0.2.9.dist-info/RECORD
