Metadata-Version: 2.4
Name: django-data-purger
Version: 0.2.9
Summary: Periodically remove data from your Django app.
License: MIT
Author: Eirik Martiniussen Sylliaas
Author-email: eirik@sylliaas.no
Requires-Python: >=3.13,<3.15
Classifier: License :: OSI Approved :: MIT License
Classifier: Programming Language :: Python :: 3
Classifier: Programming Language :: Python :: 3.13
Classifier: Programming Language :: Python :: 3.14
Requires-Dist: pydantic (>=2.11,<2.13)
